{
    "Гречневая каша рассыпчатая": {
        "Калорийность": "98,7 кКал",
        "Белки": "3,6 г",
        "Жиры": "2,2 г",
        "Углеводы": "17,1 г"
    },
    "Каша \"Янтарная\"(из пшена я яблоками)": {
        "Калорийность": "138,9 кКал",
        "Белки": "3,8 г",
        "Жиры": "6,5 г",
        "Углеводы": "17,5 г"
    },
    "Каша боярская (из пшена с изюмом)": {
        "Калорийность": "221,7 кКал",
        "Белки": "4,8 г",
        "Жиры": "14,4 г",
        "Углеводы": "19,5 г"
    },
    "Каша вязкая из пшена с тыквой": {
        "Калорийность": "158 кКал",
        "Белки": "4,2 г",
        "Жиры": "8 г",
        "Углеводы": "18,5 г"
    },
    "Каша гурьевская": {
        "Калорийность": "151,2 кКал",
        "Белки": "4,4 г",
        "Жиры": "5,4 г",
        "Углеводы": "22,6 г"
    },
    "Каша из тыквы с манкой": {
        "Калорийность": "161,5 кКал",
        "Белки": "2,8 г",
        "Жиры": "8,4 г",
        "Углеводы": "19,9 г"
    },
    "Каша манная коричневая": {
        "Калорийность": "162,1 кКал",
        "Белки": "5,3 г",
        "Жиры": "6 г",
        "Углеводы": "23,2 г"
    },
    "Каша пшенная с сушеными сливами": {
        "Калорийность": "121,3 кКал",
        "Белки": "2,4 г",
        "Жиры": "2,9 г",
        "Углеводы": "22,7 г"
    },
    "Каша рисовая с какао": {
        "Калорийность": "146,2 кКал",
        "Белки": "4,1 г",
        "Жиры": "6 г",
        "Углеводы": "20,3 г"
    },
    "Манная каша на клюквенном соке": {
        "Калорийность": "112,7 кКал",
        "Белки": "1,9 г",
        "Жиры": "4,6 г",
        "Углеводы": "17 г"
    },
    "Манная каша с морковью": {
        "Калорийность": "97,3 кКал",
        "Белки": "2,7 г",
        "Жиры": "5,6 г",
        "Углеводы": "9,7 г"
    },
    "Мучная каша": {
        "Калорийность": "95,3 кКал",
        "Белки": "3,4 г",
        "Жиры": "4,9 г",
        "Углеводы": "10,2 г"
    },
    "Рисовая каша с черносливом": {
        "Калорийность": "128,5 кКал",
        "Белки": "1,9 г",
        "Жиры": "2,4 г",
        "Углеводы": "26,4 г"
    },
    "Рисовая с абрикосами по-венгерски": {
        "Калорийность": "119,7 кКал",
        "Белки": "2,6 г",
        "Жиры": "0,3 г",
        "Углеводы": "28,5 г"
    },
    "Яблочно-манная каша": {
        "Калорийность": "128,4 кКал",
        "Белки": "1,9 г",
        "Жиры": "4,3 г",
        "Углеводы": "22 г"
    },
    "Яичная каша (натуральная)": {
        "Калорийность": "180,3 кКал",
        "Белки": "10,3 г",
        "Жиры": "11 г",
        "Углеводы": "10,8 г"
    },
    "Яичная каша с овощами или грибами": {
        "Калорийность": "261 кКал",
        "Белки": "15,9 г",
        "Жиры": "13,2 г",
        "Углеводы": "20,9 г"
    },
    "Ячневая каша с картофелем": {
        "Калорийность": "48,6 кКал",
        "Белки": "1,8 г",
        "Жиры": "1 г",
        "Углеводы": "8,7 г"
    }
}